quick_secure/__init__.py
quick_secure-0.2.1.1.dist-info/METADATA
quick_secure-0.2.1.1.dist-info/WHEEL
quick_secure-0.2.1.1.dist-info/top_level.txt
quick_secure-0.2.1.1.dist-info/RECORD
