Metadata-Version: 2.1
Name: quick-secure
Version: 0.2.1.1
Summary: UNKNOWN
Home-page: https://github.com/ahmadfaizalbh/quick_secure
Author: Ahmad Faizal B H
Author-email: ahmadfaizalbh726@gmail.com
License: MIT
Keywords: Quick secure is for encryption and decryption of string
Platform: Windows
Platform: Linux
Platform: Solaris
Platform: Mac OS-X
Platform: Unix
